agent_expert_panel/__init__.py
agent_expert_panel/main.py
agent_expert_panel/panel.py
agent_expert_panel/virtual_panel.py
agent_expert_panel/agents/__init__.py
agent_expert_panel/agents/create_agent.py
agent_expert_panel/agents/web_research_agent.py
agent_expert_panel/agents/mai_dxo/__init__.py
agent_expert_panel/agents/mai_dxo/action_coordinator.py
agent_expert_panel/agents/mai_dxo/base_agent.py
agent_expert_panel/agents/mai_dxo/critical_challenger.py
agent_expert_panel/agents/mai_dxo/quality_validator.py
agent_expert_panel/agents/mai_dxo/resource_optimizer.py
agent_expert_panel/agents/mai_dxo/stakeholder_steward.py
agent_expert_panel/agents/mai_dxo/strategic_analyst.py
agent_expert_panel/configs/advocate.yaml
agent_expert_panel/configs/critic.yaml
agent_expert_panel/configs/innovator.yaml
agent_expert_panel/configs/pragmatist.yaml
agent_expert_panel/configs/research_specialist.yaml
agent_expert_panel/configs/web_research_specialist.yaml
agent_expert_panel/information/__init__.py
agent_expert_panel/information/gatekeeper.py
agent_expert_panel/memory/__init__.py
agent_expert_panel/memory/mem0_manager.py
agent_expert_panel/models/__init__.py
agent_expert_panel/models/config.py
agent_expert_panel/models/consensus.py
agent_expert_panel/models/file_attachment.py
agent_expert_panel/models/mai_dxo.py
agent_expert_panel/models/model_info.py
agent_expert_panel/models/observability.py
agent_expert_panel/models/panel.py
agent_expert_panel/models/virtual_panel.py
agent_expert_panel/observability/__init__.py
agent_expert_panel/observability/langfuse_tracer.py
agent_expert_panel/observability/observability_manager.py
agent_expert_panel/orchestration/__init__.py
agent_expert_panel/orchestration/magentic_one.py
agent_expert_panel/orchestration/mixture_of_agents.py
agent_expert_panel/orchestration/multi_agent_debate.py
agent_expert_panel/orchestration/round_robin.py
agent_expert_panel/orchestration/selector.py
agent_expert_panel/orchestration/society_of_mind.py
agent_expert_panel-0.5.2.dist-info/METADATA
agent_expert_panel-0.5.2.dist-info/WHEEL
agent_expert_panel-0.5.2.dist-info/entry_points.txt
agent_expert_panel-0.5.2.dist-info/top_level.txt
agent_expert_panel-0.5.2.dist-info/RECORD
