Metadata-Version: 2.4
Name: agent-expert-panel
Version: 0.5.2
Summary: A panel of experts that will solve problems and discuss topics
Author-email: Zachary Bloss <zacharybloss@gmail.com>
Project-URL: Homepage, https://github.com/zbloss/agent-expert-panel
Project-URL: Repository, https://github.com/zbloss/agent-expert-panel
Project-URL: Documentation, https://github.com/zbloss/agent-expert-panel#readme
Project-URL: Issues, https://github.com/zbloss/agent-expert-panel/issues
Keywords: ai,agents,expert-panel,multi-agent,discussion
Classifier: Development Status :: 3 - Alpha
Classifier: Intended Audience :: Developers
Classifier: Programming Language :: Python :: 3
Classifier: Programming Language :: Python :: 3.12
Classifier: Topic :: Scientific/Engineering :: Artificial Intelligence
Classifier: Topic :: Software Development :: Libraries :: Python Modules
Requires-Python: <3.13,>=3.12
Requires-Dist: autogen-agentchat>=0.6.4
Requires-Dist: autogen-core>=0.6.4
Requires-Dist: autogen-ext[mcp,mem0-local,openai]>=0.6.4
Requires-Dist: graphrag<2.0.0,>=1.0.0
Requires-Dist: langchain-tavily>=0.2.0
Requires-Dist: langfuse>=2.61.1
Requires-Dist: playwright>=1.45.0
Requires-Dist: pydantic>=2.11.7
Requires-Dist: pydantic-settings[yaml]>=2.10.1
Requires-Dist: PyYAML>=6.0.1
Requires-Dist: rich<14.0.0,>=13.9.4
Requires-Dist: tiktoken<0.9.0,>=0.8.0
Requires-Dist: typer>=0.12.0
